pydatamail_google/__init__.py
pydatamail_google/__main__.py
pydatamail_google/_version.py
pydatamail_google/local.py
pydatamail_google/base/__init__.py
pydatamail_google/base/archive.py
pydatamail_google/base/google_drive.py
pydatamail_google/base/google_mail.py
pydatamail_google/base/message.py
pydatamail_google-0.0.8.dist-info/LICENSE
pydatamail_google-0.0.8.dist-info/METADATA
pydatamail_google-0.0.8.dist-info/WHEEL
pydatamail_google-0.0.8.dist-info/entry_points.txt
pydatamail_google-0.0.8.dist-info/top_level.txt
pydatamail_google-0.0.8.dist-info/RECORD
