Metadata-Version: 2.1
Name: pydatamail-google
Version: 0.0.8
Summary: Python interface to filter emails on Google Mail.
Home-page: https://github.com/pyscioffice/pydatamail_google
Author: Jan Janssen
Author-email: jan.janssen@outlook.com
License: BSD
License-File: LICENSE
Requires-Dist: google-api-python-client (>=2.52.0)
Requires-Dist: google-auth (>=2.9.0)
Requires-Dist: google-auth-oauthlib (>=0.5.2)
Requires-Dist: tqdm (>=4.64.0)
Requires-Dist: pandas (>=1.4.3)
Requires-Dist: sqlalchemy (>=1.4.39)
Requires-Dist: numpy (>=1.23.0)
Requires-Dist: matplotlib (>=3.5.2)
Requires-Dist: pydatamail (>=0.0.9)
Provides-Extra: archive
Requires-Dist: pypdf3 (>=1.0.6) ; extra == 'archive'
Requires-Dist: email2pdf (>=0.9.9.0) ; extra == 'archive'
Provides-Extra: machinelearning
Requires-Dist: pydatamail-ml (>=0.0.2) ; extra == 'machinelearning'
